{
  "Arn": "arn:aws:iam::aws:policy/AmazonHoneycodeTeamAssociationFullAccess",
  "CreateDate": "2020-06-24T20:28:27Z",
  "DefaultVersionId": "v1",
  "IsAttachable": true,
  "Path": "/",
  "PolicyId": "ANPAZKAPJZG4JH4KLR35J",
  "PolicyName": "AmazonHoneycodeTeamAssociationFullAccess",
  "PolicyVersion": {
    "CreateDate": "2020-06-24T20:28:27Z",
    "Document": {
      "Statement": [
        {
          "Action": [
            "honeycode:ApproveTeamAssociation",
            "honeycode:ListTeamAssociations",
            "honeycode:RejectTeamAssociation"
          ],
          "Effect": "Allow",
          "Resource": "*"
        }
      ],
      "Version": "2012-10-17"
    },
    "IsDefaultVersion": true,
    "VersionId": "v1"
  },
  "UpdateDate": "2020-06-24T20:28:27Z"
}
