{
  "Arn": "arn:aws:iam::aws:policy/AmazonAugmentedAIHumanLoopFullAccess",
  "CreateDate": "2019-12-03T16:20:47Z",
  "DefaultVersionId": "v1",
  "IsAttachable": true,
  "Path": "/",
  "PolicyId": "ANPAZKAPJZG4DLDNVPZG4",
  "PolicyName": "AmazonAugmentedAIHumanLoopFullAccess",
  "PolicyVersion": {
    "CreateDate": "2019-12-03T16:20:47Z",
    "Document": {
      "Statement": [
        {
          "Action": [
            "sagemaker:*HumanLoop",
            "sagemaker:*HumanLoops"
          ],
          "Effect": "Allow",
          "Resource": "*"
        }
      ],
      "Version": "2012-10-17"
    },
    "IsDefaultVersion": true,
    "VersionId": "v1"
  },
  "UpdateDate": "2019-12-03T16:20:47Z"
}
