{
  "Arn": "arn:aws:iam::aws:policy/AmazonAppStreamReadOnlyAccess",
  "CreateDate": "2015-02-06T18:40:10Z",
  "DefaultVersionId": "v3",
  "IsAttachable": true,
  "Path": "/",
  "PolicyId": "ANPAJXIFDGB4VBX23DX7K",
  "PolicyName": "AmazonAppStreamReadOnlyAccess",
  "PolicyVersion": {
    "CreateDate": "2025-10-22T17:04:08Z",
    "Document": {
      "Statement": [
        {
          "Action": [
            "appstream:Describe*",
            "appstream:List*"
          ],
          "Effect": "Allow",
          "Resource": "*"
        }
      ],
      "Version": "2012-10-17"
    },
    "IsDefaultVersion": true,
    "VersionId": "v3"
  },
  "UpdateDate": "2025-10-22T17:04:08Z"
}
