{
  "Arn": "arn:aws:iam::aws:policy/AWSBudgetsReadOnlyAccess",
  "CreateDate": "2020-10-15T17:18:28Z",
  "DefaultVersionId": "v2",
  "IsAttachable": true,
  "Path": "/",
  "PolicyId": "ANPAZKAPJZG4EZCFS6BHW",
  "PolicyName": "AWSBudgetsReadOnlyAccess",
  "PolicyVersion": {
    "CreateDate": "2024-06-17T17:41:25Z",
    "Document": {
      "Statement": [
        {
          "Action": [
            "aws-portal:ViewBilling",
            "budgets:Describe*",
            "budgets:ListTagsForResource",
            "budgets:ViewBudget"
          ],
          "Effect": "Allow",
          "Resource": "*",
          "Sid": "AWSBudgetsReadOnlyAccess"
        }
      ],
      "Version": "2012-10-17"
    },
    "IsDefaultVersion": true,
    "VersionId": "v2"
  },
  "UpdateDate": "2024-06-17T17:41:25Z"
}
