{
  "Arn": "arn:aws:iam::aws:policy/service-role/AWSIoTDeviceDefenderReplaceDefaultPolicyMitigationAction",
  "CreateDate": "2019-08-07T17:04:57Z",
  "DefaultVersionId": "v1",
  "IsAttachable": true,
  "Path": "/service-role/",
  "PolicyId": "ANPAZKAPJZG4HN4VCIBCR",
  "PolicyName": "AWSIoTDeviceDefenderReplaceDefaultPolicyMitigationAction",
  "PolicyVersion": {
    "CreateDate": "2019-08-07T17:04:57Z",
    "Document": {
      "Statement": [
        {
          "Action": [
            "iot:CreatePolicyVersion"
          ],
          "Effect": "Allow",
          "Resource": [
            "*"
          ]
        }
      ],
      "Version": "2012-10-17"
    },
    "IsDefaultVersion": true,
    "VersionId": "v1"
  },
  "UpdateDate": "2019-08-07T17:04:57Z"
}
