{
  "Arn": "arn:aws:iam::aws:policy/IAMAccessAnalyzerReadOnlyAccess",
  "CreateDate": "2019-12-02T17:12:53Z",
  "DefaultVersionId": "v1",
  "IsAttachable": true,
  "Path": "/",
  "PolicyId": "ANPAZKAPJZG4GY4R3GAPM",
  "PolicyName": "IAMAccessAnalyzerReadOnlyAccess",
  "PolicyVersion": {
    "CreateDate": "2019-12-02T17:12:53Z",
    "Document": {
      "Statement": [
        {
          "Action": [
            "access-analyzer:Get*",
            "access-analyzer:List*"
          ],
          "Effect": "Allow",
          "Resource": "*"
        }
      ],
      "Version": "2012-10-17"
    },
    "IsDefaultVersion": true,
    "VersionId": "v1"
  },
  "UpdateDate": "2019-12-02T17:12:53Z"
}
