{
  "Arn": "arn:aws:iam::aws:policy/aws-service-role/Route53ResolverServiceRolePolicy",
  "CreateDate": "2020-08-12T17:47:24Z",
  "DefaultVersionId": "v1",
  "IsAttachable": true,
  "Path": "/aws-service-role/",
  "PolicyId": "ANPAZKAPJZG4AEMJZANMJ",
  "PolicyName": "Route53ResolverServiceRolePolicy",
  "PolicyVersion": {
    "CreateDate": "2020-08-12T17:47:24Z",
    "Document": {
      "Statement": [
        {
          "Action": [
            "logs:CreateLogDelivery",
            "logs:DeleteLogDelivery",
            "logs:DescribeLogGroups",
            "logs:DescribeResourcePolicies",
            "logs:GetLogDelivery",
            "logs:ListLogDeliveries",
            "logs:UpdateLogDelivery",
            "s3:GetBucketPolicy"
          ],
          "Effect": "Allow",
          "Resource": "*"
        }
      ],
      "Version": "2012-10-17"
    },
    "IsDefaultVersion": true,
    "VersionId": "v1"
  },
  "UpdateDate": "2020-08-12T17:47:24Z"
}
