{
  "Arn": "arn:aws:iam::aws:policy/TranslateFullAccess",
  "CreateDate": "2018-11-27T23:36:20Z",
  "DefaultVersionId": "v1",
  "IsAttachable": true,
  "Path": "/",
  "PolicyId": "ANPAIAPOAEI2VFQYUK5RY",
  "PolicyName": "TranslateFullAccess",
  "PolicyVersion": {
    "CreateDate": "2018-11-27T23:36:20Z",
    "Document": {
      "Statement": [
        {
          "Action": [
            "cloudwatch:GetMetricStatistics",
            "cloudwatch:ListMetrics",
            "comprehend:DetectDominantLanguage",
            "translate:*"
          ],
          "Effect": "Allow",
          "Resource": "*"
        }
      ],
      "Version": "2012-10-17"
    },
    "IsDefaultVersion": true,
    "VersionId": "v1"
  },
  "UpdateDate": "2018-11-27T23:36:20Z"
}
